ailab/__init__.py
ailab/atp_dataset/__init__.py
ailab/atp_dataset/ailab_api.py
ailab/atp_dataset/constant.py
ailab/atp_dataset/data_info.json
ailab/atp_dataset/dataset.py
ailab/atp_dataset/huggingface_api.py
ailab/atp_dataset/test/1111.json
ailab/atp_dataset/test/csv/1111.xlsx
ailab/atp_dataset/test/json/merged.jsonl
ailab/atp_dataset/test/json/merged_cn.jsonl
ailab/atp_dataset/test/json/test.json
ailab/atp_dataset/test/json/test_0.json
ailab/atp_dataset/test/json/test_1.json
ailab/atp_dataset/test/json/test_2.json
ailab/atp_dataset/test/json/test_3.json
ailab/atp_dataset/test/json/test_4.json
ailab/atp_dataset/test/json/test_5.json
ailab/atp_dataset/test/json/test_6.json
ailab/atp_dataset/test/json/test_7.json
ailab/atp_dataset/test/json/test_8.json
ailab/atp_dataset/test/json/test_9.json
ailab/atp_dataset/test/test.jsonl.json
ailab/atp_dataset/test/ttt.jsonl
ailab/atp_evaluation/benchmarks/__init__.py
ailab/atp_evaluation/benchmarks/base.py
ailab/atp_evaluation/benchmarks/ceval.py
ailab/atp_evaluation/benchmarks/harness.py
ailab/atp_evaluation/benchmarks/mmlu.py
ailab/atp_evaluation/build.py
ailab/atp_evaluation/constant.py
ailab/atp_evaluation/evaluator.py
ailab/atp_evaluation/models/__init__.py
ailab/atp_evaluation/models/base.py
ailab/atp_evaluation/models/chatglm.py
ailab/atp_evaluation/models/llama.py
ailab/atp_finetuner/__init__.py
ailab/atp_finetuner/accelerator/__init__.py
ailab/atp_finetuner/accelerator/accelerator.py
ailab/atp_finetuner/build.py
ailab/atp_finetuner/constant.py
ailab/atp_finetuner/datacollator/__init__.py
ailab/atp_finetuner/datacollator/datacollator.py
ailab/atp_finetuner/datacollator/dc_for_alpaca.py
ailab/atp_finetuner/datacollator/dc_for_baichuan.py
ailab/atp_finetuner/datacollator/dc_for_chatglm.py
ailab/atp_finetuner/datacollator/dc_for_chinese_alpaca.py
ailab/atp_finetuner/datacollator/dc_for_language.py
ailab/atp_finetuner/datacollator/dc_for_token.py
ailab/atp_finetuner/datacollator/dc_for_yolos.py
pyatp-1.8.5.dist-info/LICENSE
pyatp-1.8.5.dist-info/METADATA
pyatp-1.8.5.dist-info/WHEEL
pyatp-1.8.5.dist-info/RECORD
